transactions_chile/__init__.py
transactions_chile/bank_transactions.py
transactions_chile/cli.py
transactions_chile/schemas.py
transactions_chile-0.4.0.dist-info/METADATA
transactions_chile-0.4.0.dist-info/WHEEL
transactions_chile-0.4.0.dist-info/entry_points.txt
transactions_chile-0.4.0.dist-info/licenses/LICENSE
transactions_chile-0.4.0.dist-info/RECORD
