Metadata-Version: 2.4
Name: transactions_chile
Version: 0.4.0
Summary: A command-line tool for converting bank statements from Excel to CSV format with support for several Chilean banks.
Project-URL: Homepage, https://github.com/josecannete/transactions-chile
Project-URL: Bug Tracker, https://github.com/josecannete/transactions-chile/issues
Author-email: Jose Cañete <josecannete@gmail.com>
License: MIT
License-File: LICENSE
Classifier: Intended Audience :: Developers
Classifier: License :: OSI Approved :: MIT License
Classifier: Operating System :: OS Independent
Classifier: Programming Language :: Python :: 3
Classifier: Topic :: Office/Business :: Financial
Classifier: Topic :: Utilities
Requires-Python: >=3.11
Requires-Dist: click>=8.1.0
Requires-Dist: openpyxl>=3.1.0
Requires-Dist: pandas>=2.0.0
Requires-Dist: pandera>=0.23.1
Requires-Dist: rich>=13.4.0
Requires-Dist: xlrd>=2.0.1
